<?xml version="1.0" encoding="utf-8" ?>
<dwsync>
<file name="CONTACT.html.mno" server="ftp.ateliermorales.com/www/" local="130358720937865968" remote="130359031800000000" Dst="1" />
<file name="PRESS.html.mno" server="ftp.ateliermorales.com/www/" local="130363484368742570" remote="130363485000000000" Dst="1" />
<file name="CV.html.mno" server="ftp.ateliermorales.com/www/" local="130363370934384496" remote="130359067800000000" Dst="1" />
<file name="GALERIES.html.mno" server="ftp.ateliermorales.com/www/" local="130358719255839762" remote="130359031800000000" Dst="1" />
<file name="ARCHITECTURE habanita.html.mno" server="ftp.ateliermorales.com/www/" local="130358718767711843" remote="130359031800000000" Dst="1" />
<file name="ARCHITECTURE foires.html.mno" server="ftp.ateliermorales.com/www/" local="130358718324656501" remote="130359031800000000" Dst="1" />
<file name="ARCHITECTURE el bierzo.html.mno" server="ftp.ateliermorales.com/www/" local="130358716185944174" remote="130359031800000000" Dst="1" />
<file name="ARCHITECTURE seoul.html.mno" server="ftp.ateliermorales.com/www/" local="130358715607371082" remote="130359031800000000" Dst="1" />
<file name="ARCHITECTURE log havane.html.mno" server="ftp.ateliermorales.com/www/" local="130358714835366926" remote="130359031800000000" Dst="1" />
<file name="ARCHITECTURE montsouris.html.mno" server="ftp.ateliermorales.com/www/" local="130360974522163862" remote="130359067800000000" Dst="1" />
<file name="ARCHITECTURE treplay.html.mno" server="ftp.ateliermorales.com/www/" local="130358713420425996" remote="130359031800000000" Dst="1" />
<file name="BOHIOS.html.mno" server="ftp.ateliermorales.com/www/" local="130358712180025049" remote="130359031800000000" Dst="1" />
<file name="PEREGRINOS.html.mno" server="ftp.ateliermorales.com/www/" local="130363473802828234" remote="130359067800000000" Dst="1" />
<file name="VIAJE EQUINOCCIAL.html.mno" server="ftp.ateliermorales.com/www/" local="130363479825702723" remote="130359067800000000" Dst="1" />
<file name="LOS BALNEARIOS.html.mno" server="ftp.ateliermorales.com/www/" local="130363478640654942" remote="130359067800000000" Dst="1" />
<file name="DEUXIEME SEXE.htm.mno" server="ftp.ateliermorales.com/www/" local="130363475689806163" remote="130359068400000000" Dst="1" />
<file name="HERMANOS ENEMIGOS.html.mno" server="ftp.ateliermorales.com/www/" local="130363464925570484" remote="130359068400000000" Dst="1" />
<file name="HOMENAJE A SAKINEH.html.mno" server="ftp.ateliermorales.com/www/" local="130363440797760452" remote="130363467600000000" Dst="1" />
<file name="HOMENAJE A MONET.html.mno" server="ftp.ateliermorales.com/www/" local="130363440674023375" remote="130359068400000000" Dst="1" />
<file name="PUBLICATIONS.html.mno" server="ftp.ateliermorales.com/www/" local="130361148562457821" remote="130361151000000000" Dst="1" />
<file name="ARCHITECTURE.html.mno" server="ftp.ateliermorales.com/www/" local="130361127789579680" remote="130361151000000000" Dst="1" />
</dwsync>